an_quickviper2/__init__.py
an_quickviper2/quickviper2.py
an_quickviper2-1.3.0.dist-info/licenses/LICENSE
an_quickviper2-1.3.0.dist-info/METADATA
an_quickviper2-1.3.0.dist-info/WHEEL
an_quickviper2-1.3.0.dist-info/top_level.txt
an_quickviper2-1.3.0.dist-info/RECORD
