Metadata-Version: 2.4
Name: an_quickviper2
Version: 1.3.0
Summary: A package for an_quickviper2.
Home-page: https://github.com/Atsushi888/Atsushi888
Author: Atsushi888
Author-email: Atsushi888 <vtgrotxu@gmail.com>
Project-URL: Homepage, https://github.com/Atsushi888/an_quickviper2
Project-URL: Repository, https://github.com/Atsushi888/an_quickviper2
Requires-Python: >=3.6
License-File: LICENSE
Requires-Dist: an_DebugHelper>=1.3.2
Requires-Dist: an_UniqueEnvVar>=0.1.5
Requires-Dist: an_ToolKit>=0.1.4
Dynamic: author
Dynamic: home-page
Dynamic: license-file
Dynamic: requires-python
